screensync/__init__.py
screensync/app.py
screensync/check.py
screensync/ui.py
screensync/assets/IMG_0877.JPG
screensync/assets/ScreenSync.ico
screensync/assets/img.png
screensync/assets/screensync-banner.png
screensync/assets/settings_screenshot.png
screensync/screen_sync/__init__.py
screensync/screen_sync/bulb_factory.py
screensync/screen_sync/bulb_types.py
screensync/screen_sync/color_processing.py
screensync/screen_sync/config_manager.py
screensync/screen_sync/coordinator.py
screensync/screen_sync/graph.py
screensync/screen_sync/main.py
screensync/screen_sync/rate_limiter.py
screensync/screen_sync/stats.py
screensync/screen_sync/bulb_control/__init__.py
screensync/screen_sync/bulb_control/abstract_bulb_control.py
screensync/screen_sync/bulb_control/magichome_bulb.py
screensync/screen_sync/bulb_control/tuya_bulb.py
screensync/screen_sync/bulb_control/zigbee_bulb.py
screensync/screen_sync/ui/__init__.py
screensync/screen_sync/ui/add_bulb.py
screensync/screen_sync/ui/remove_bulb.py
screensync/tests/__init__.py
screensync/tests/test_bulb_control.py
screensync/tests/test_bulb_factory.py
screensync/tests/test_color_processing.py
screensync/tests/test_config_manager.py
screensync/tests/test_configuration.py
screensync/tests/test_ui.py
ScreenSync-0.0.6.dist-info/LICENSE
ScreenSync-0.0.6.dist-info/METADATA
ScreenSync-0.0.6.dist-info/WHEEL
ScreenSync-0.0.6.dist-info/entry_points.txt
ScreenSync-0.0.6.dist-info/top_level.txt
ScreenSync-0.0.6.dist-info/RECORD
