Metadata-Version: 2.1
Name: ScreenSync
Version: 0.0.6
Summary: A Python tool for synchronizing screen colors with smart bulbs.
Home-page: https://github.com/dewgenenny/ScreenSync
Author: Tom George
Author-email: tom@penberth.com
Classifier: Development Status :: 3 - Alpha
Classifier: Intended Audience :: Developers
Classifier: Natural Language :: English
Classifier: Programming Language :: Python :: 3
Classifier: Programming Language :: Python :: 3.8
Classifier: Programming Language :: Python :: 3.9
Classifier: Operating System :: OS Independent
Requires-Python: >=3.6
License-File: LICENSE
Requires-Dist: tinytuya >=1.2.0
Requires-Dist: Pillow >=8.0.0
Requires-Dist: paho-mqtt
Requires-Dist: matplotlib
Requires-Dist: mss
Requires-Dist: platformdirs
Requires-Dist: flux-led
